translator/__init__.py
translator/_version.py
rms_translator-0.0.3.dist-info/LICENSE
rms_translator-0.0.3.dist-info/METADATA
rms_translator-0.0.3.dist-info/WHEEL
rms_translator-0.0.3.dist-info/top_level.txt
rms_translator-0.0.3.dist-info/RECORD
